aiortc/__init__.py
aiortc/clock.py
aiortc/events.py
aiortc/exceptions.py
aiortc/jitterbuffer.py
aiortc/mediastreams.py
aiortc/py.typed
aiortc/rate.py
aiortc/rtcconfiguration.py
aiortc/rtcdatachannel.py
aiortc/rtcdtlstransport.py
aiortc/rtcicetransport.py
aiortc/rtcpeerconnection.py
aiortc/rtcrtpparameters.py
aiortc/rtcrtpreceiver.py
aiortc/rtcrtpsender.py
aiortc/rtcrtptransceiver.py
aiortc/rtcsctptransport.py
aiortc/rtcsessiondescription.py
aiortc/rtp.py
aiortc/sdp.py
aiortc/stats.py
aiortc/utils.py
aiortc/codecs/__init__.py
aiortc/codecs/base.py
aiortc/codecs/g711.py
aiortc/codecs/g722.py
aiortc/codecs/h264.py
aiortc/codecs/opus.py
aiortc/codecs/vpx.py
aiortc/contrib/__init__.py
aiortc/contrib/media.py
aiortc/contrib/signaling.py
aiortc_dimos-1.14.0.dist-info/licenses/LICENSE
aiortc_dimos-1.14.0.dist-info/METADATA
aiortc_dimos-1.14.0.dist-info/WHEEL
aiortc_dimos-1.14.0.dist-info/top_level.txt
aiortc_dimos-1.14.0.dist-info/RECORD
